giz_exceptions/__init__.py
giz_exceptions/handler.py
giz_exceptions/paas/__init__.py
giz_exceptions/paas/exceptions/__init__.py
giz_exceptions/paas/exceptions/base.py
giz_exceptions/paas/exceptions/data.py
giz_exceptions/paas/exceptions/system.py
giz_exceptions/paas/exceptions/business/__init__.py
giz_exceptions/paas/exceptions/business/base.py
giz_exceptions/paas/exceptions/business/device.py
giz_exceptions/paas/exceptions/business/gdcs.py
giz_exceptions/paas/exceptions/business/preauth.py
giz_exceptions/paas/exceptions/business/product.py
giz_exceptions-0.0.8.dist-info/LICENSE
giz_exceptions-0.0.8.dist-info/METADATA
giz_exceptions-0.0.8.dist-info/WHEEL
giz_exceptions-0.0.8.dist-info/top_level.txt
giz_exceptions-0.0.8.dist-info/RECORD
