Metadata-Version: 2.1
Name: giz-exceptions
Version: 0.0.8
Summary: Exceptions for Gizwits PaaS
Home-page: UNKNOWN
Author: Matthew Pang
Author-email: mpang@gizwits.com
License: UNKNOWN
Platform: UNKNOWN
Classifier: Programming Language :: Python :: 3
Classifier: License :: OSI Approved :: MIT License
Classifier: Operating System :: OS Independent
Requires-Python: >=3.6
Requires-Dist: djangorestframework
